vumi_message_store-0.1.4.dist-info/WHEEL
vumi_message_store-0.1.4.dist-info/DESCRIPTION.rst
vumi_message_store-0.1.4.dist-info/METADATA
vumi_message_store-0.1.4.dist-info/RECORD
vumi_message_store-0.1.4.dist-info/metadata.json
vumi_message_store-0.1.4.dist-info/top_level.txt
vumi_message_store/riak_backend.py
vumi_message_store/__init__.py
vumi_message_store/memory_backend_manager.py
vumi_message_store/interfaces.py
vumi_message_store/models.py
vumi_message_store/migrators.py
vumi_message_store/batch_info_cache.py
vumi_message_store/message_store.py
vumi_message_store/tests/helpers.py
vumi_message_store/tests/test_riak_backend.py
vumi_message_store/tests/__init__.py
vumi_message_store/tests/test_message_store.py
vumi_message_store/tests/test_batch_info_cache.py
vumi_message_store/tests/test_memory_backend_manager.py
vumi_message_store/tests/test_migrators.py
vumi_message_store/tests/test_models.py
vumi_message_store/tests/old_models.py
vumi_message_store/tests/test_test_helpers.py
vumi_message_store/api/message_export_worker.py
vumi_message_store/api/__init__.py
vumi_message_store/api/message_export_formatters.py
vumi_message_store/api/message_export_resources.py
vumi_message_store/api/tests/__init__.py
vumi_message_store/api/tests/test_message_export_worker.py
vumi_message_store/api/tests/test_message_export_formatters.py
