Metadata-Version: 2.0
Name: vumi-message-store
Version: 0.1.4
Summary: A persistent store for vumi messages.
Home-page: http://github.com/praekelt/vumi-message-store
Author: Praekelt Foundation
Author-email: dev@praekeltfoundation.org
License: BSD
Platform: UNKNOWN
Classifier: Development Status :: 4 - Beta
Classifier: Intended Audience :: Developers
Classifier: License :: OSI Approved :: BSD License
Classifier: Operating System :: POSIX
Classifier: Programming Language :: Python
Classifier: Topic :: Software Development :: Libraries :: Python Modules
Classifier: Topic :: System :: Networking
Requires-Dist: vumi (>=0.5.21)
Requires-Dist: Twisted (>=13.1.0)
